pdfmerger/__init__.py
pdfmerger/merge.py
pdfmerger/mergepdfs.py
mergepdfs-0.9.2.dist-info/LICENSE
mergepdfs-0.9.2.dist-info/METADATA
mergepdfs-0.9.2.dist-info/WHEEL
mergepdfs-0.9.2.dist-info/entry_points.txt
mergepdfs-0.9.2.dist-info/top_level.txt
mergepdfs-0.9.2.dist-info/RECORD
