Metadata-Version: 2.1
Name: mergepdfs
Version: 0.9.2
Summary: Python command line program for merging multiple PDF-files to one PDF
Home-page: https://github.com/HermitOS/mergepdfs
Author: Isabel Sandstrøm, Terje Sandstrom,
Author-email: isabel@hermit.no
License: UNKNOWN
Platform: UNKNOWN
Classifier: Programming Language :: Python :: 3
Classifier: License :: OSI Approved :: MIT License
Classifier: Operating System :: OS Independent
Requires-Python: >=3.6
License-File: LICENSE
Requires-Dist: PyPDF2 (>=1.26.0)
